klpt/__init__.py
klpt/att_analyze.py
klpt/configuration.py
klpt/preprocess.py
klpt/stem.py
klpt/tokenize.py
klpt/transliterate.py
klpt/utility.py
klpt/data/ckb-Arab.aff
klpt/data/ckb-Arab.dic
klpt/data/ckb-morphemes.json
klpt/data/default-options.json
klpt/data/kmr-Latn.aff
klpt/data/kmr-Latn.att
klpt/data/kmr-Latn.dic
klpt/data/kmr-morphemes.json
klpt/data/lexicon_ckb_arab.json
klpt/data/lexicon_ckb_latn.json
klpt/data/lexicon_kmr_latn.json
klpt/data/preprocess_map.json
klpt/data/stopwords.json
klpt/data/test_cases.json
klpt/data/test_cases_stem.json
klpt/data/test_cases_tokenize.json
klpt/data/tokenize.json
klpt/data/wergor.json
klpt-0.1.7.dist-info/LICENSE
klpt-0.1.7.dist-info/METADATA
klpt-0.1.7.dist-info/WHEEL
klpt-0.1.7.dist-info/top_level.txt
klpt-0.1.7.dist-info/RECORD
