Metadata-Version: 2.1
Name: klpt
Version: 0.1.7
Summary: Kurdish Language Processing Toolkit
Home-page: https://github.com/sinaahmadi/klpt
Author: Sina Ahmadi
Author-email: ahmadi.sina@outlook.com
License: CC BY-SA 4.0
Requires-Python: >=3.6
License-File: LICENSE
Requires-Dist: chunspell ==2.0.4
